<?xml version="1.0" encoding="utf-8" ?>
<dwsync>
<file name="smiley-cry.gif" server="editor.id/public_html/" local="130883844618468210" remote="129113316000000000" Dst="0" />
<file name="smiley-cool.gif" server="editor.id/public_html/" local="130883844626059802" remote="129113316000000000" Dst="0" />
<file name="smiley-embarassed.gif" server="editor.id/public_html/" local="130883844628891688" remote="129113316000000000" Dst="0" />
<file name="smiley-foot-in-mouth.gif" server="editor.id/public_html/" local="130883844629522115" remote="129113316000000000" Dst="0" />
<file name="smiley-innocent.gif" server="editor.id/public_html/" local="130883844633726726" remote="129113316000000000" Dst="0" />
<file name="smiley-frown.gif" server="editor.id/public_html/" local="130883844634387165" remote="129113316000000000" Dst="0" />
<file name="smiley-kiss.gif" server="editor.id/public_html/" local="130883844634977574" remote="129113316000000000" Dst="0" />
<file name="smiley-laughing.gif" server="editor.id/public_html/" local="130883844640574901" remote="129113316000000000" Dst="0" />
<file name="smiley-money-mouth.gif" server="editor.id/public_html/" local="130883844641125253" remote="129113316000000000" Dst="0" />
<file name="smiley-sealed.gif" server="editor.id/public_html/" local="130883844641935792" remote="129113316000000000" Dst="0" />
<file name="smiley-smile.gif" server="editor.id/public_html/" local="130883844647049857" remote="129113316000000000" Dst="0" />
<file name="smiley-surprised.gif" server="editor.id/public_html/" local="130883844647640250" remote="129113316000000000" Dst="0" />
<file name="smiley-tongue-out.gif" server="editor.id/public_html/" local="130883844648280675" remote="129113316000000000" Dst="0" />
<file name="smiley-undecided.gif" server="editor.id/public_html/" local="130883844653308965" remote="129113316000000000" Dst="0" />
<file name="smiley-wink.gif" server="editor.id/public_html/" local="130883844654729884" remote="129113316000000000" Dst="0" />
<file name="smiley-yell.gif" server="editor.id/public_html/" local="130883844654729884" remote="129113316000000000" Dst="0" />
</dwsync>